Workbook
Name Contacts: 'Mailing list'!$C$1:$C$54

Sheet Mailing list
A1: Sponsor | B1: LastName | C1: FirstName | D1: Amount due | E1: Options | F1: Apparel | G1: Total | H1: Paid | I1: Balance
A3: Bro | B3: Alford | C3: Kyle | E3: =+Options!W3 -> 0 | G3: =SUM(D3:F3) -> 0 | I3: =+G3-H3 -> 0
A4: Sheik | B4: Bartlett | C4: Stacy | E4: =+Options!W4 -> 0 | G4: =SUM(D4:F4) -> 0 | I4: =+G4-H4 -> 0
A5: Dieterle | B5: Blankenburg | C5: Jeff | E5: =+Options!W5 -> 0 | G5: =SUM(D5:F5) -> 0 | I5: =+G5-H5 -> 0
A6: Slick/Gsta | B6: Bender | C6: Kyle | E6: =+Options!W6 -> 0 | G6: =SUM(D6:F6) -> 0 | I6: =+G6-H6 -> 0
A7: Patch | B7: Boland | C7: Pat | E7: =+Options!W7 -> 0 | G7: =SUM(D7:F7) -> 0 | I7: =+G7-H7 -> 0
A8: Gstan | B8: Brown | C8: Miles | E8: =+Options!W8 -> 0 | G8: =SUM(D8:F8) -> 0 | I8: =+G8-H8 -> 0
A9: Hood | B9: Buckey | C9: Dan | E9: =+Options!W9 -> 0 | G9: =SUM(D9:F9) -> 0 | I9: =+G9-H9 -> 0
A10: JT | B10: Carlstrom | C10: Brian | E10: =+Options!W10 -> 0 | G10: =SUM(D10:F10) -> 0 | I10: =+G10-H10 -> 0
A11: Gus | B11: Cobleigh | C11: Wayne | E11: =+Options!W11 -> 0 | G11: =SUM(D11:F11) -> 0 | I11: =+G11-H11 -> 0
A12: Whitey | B12: Combs | C12: Adam | E12: =+Options!W12 -> 0 | G12: =SUM(D12:F12) -> 0 | I12: =+G12-H12 -> 0
A13: Butter | B13: Dosky | C13: Rick | E13: =+Options!W13 -> 0 | G13: =SUM(D13:F13) -> 0 | I13: =+G13-H13 -> 0
A14: Butter | B14: Flanagan | C14: Brian | E14: =+Options!W14 -> 0 | G14: =SUM(D14:F14) -> 0 | I14: =+G14-H14 -> 0
... A27: Gstan | B27: Kaniecki | C27: Mark | E27: =+Options!W27 -> 0 | G27: =SUM(D27:F27) -> 0 | I27: =+G27-H27 -> 0
A28: Gstan | B28: Kaniecki | C28: Stan
A29: Monte | B29: Kassap | C29: Grant | E29: =+Options!W29 -> 0 | G29: =SUM(D29:F29) -> 0 | I29: =+G29-H29 -> 0
A30: Sheik | B30: Kellas | C30: Tom | E30: =+Options!W30 -> 0 | G30: =SUM(D30:F30) -> 0 | I30: =+G30-H30 -> 0
A31: Sensei | B31: Kelly | C31: Dan | E31: =+Options!W31 -> 0 | G31: =SUM(D31:F31) -> 0 | I31: =+G31-H31 -> 0
A32: Quack | B32: Kierner | C32: Rick | E32: =+Options!W32 -> 0 | G32: =SUM(D32:F32) -> 0 | I32: =+G32-H32 -> 0
A33: JT | B33: Langdon | C33: Matt | E33: =+Options!W33 -> 0 | G33: =SUM(D33:F33) -> 0 | I33: =+G33-H33 -> 0
A34: Butter | B34: Long | C34: Greg | E34: =+Options!W34 -> 0 | G34: =SUM(D34:F34) -> 0 | I34: =+G34-H34 -> 0
A35: Sheik | B35: Long | C35: Mike | E35: =+Options!W35 -> 0 | G35: =SUM(D35:F35) -> 0 | I35: =+G35-H35 -> 0
A36: Slick/Gsta | B36: Long | C36: Scott | E36: =+Options!W36 -> 0 | G36: =SUM(D36:F36) -> 0 | I36: =+G36-H36 -> 0
A37: Butter | B37: Lyme | C37: Brett | E37: =+Options!W37 -> 0 | G37: =SUM(D37:F37) -> 0 | I37: =+G37-H37 -> 0
A38: Patch | B38: Marshall | C38: Al | E38: =+Options!W38 -> 0 | G38: =SUM(D38:F38) -> 0 | I38: =+G38-H38 -> 0
A39: Butter | B39: McFarland | C39: Don | E39: =+Options!W39 -> 0 | G39: =SUM(D39:F39) -> 0 | I39: =+G39-H39 -> 0
A40: Butter | B40: Melick | C40: Eric
A41: JT | B41: Miller | C41: Christian | E41: =+Options!W41 -> 0 | G41: =SUM(D41:F41) -> 0 | I41: =+G41-H41 -> 0
A42: Monte | B42: Montgomery | C42: Dan | E42: =+Options!W42 -> 0 | G42: =SUM(D42:F42) -> 0 | I42: =+G42-H42 -> 0
A43: JT | B43: Montgomery | C43: Mark | E43: =+Options!W43 -> 0 | G43: =SUM(D43:F43) -> 0 | I43: =+G43-H43 -> 0
A44: Brent | B44: Moore | C44: Jeff | E44: =+Options!W44 -> 0 | G44: =SUM(D44:F44) -> 0 | I44: =+G44-H44 -> 0
A45: Bro | B45: Mullins | C45: Kevin | E45: =+Options!W45 -> 0 | G45: =SUM(D45:F45) -> 0 | I45: =+G45-H45 -> 0
A46: BDubs | B46: Mullins | C46: Kurt | E46: =+Options!W46 -> 0 | G46: =SUM(D46:F46) -> 0 | I46: =+G46-H46 -> 0
A47: Monte | B47: Palazzolo | C47: Sal | E47: =+Options!W47 -> 0 | G47: =SUM(D47:F47) -> 0 | I47: =+G47-H47 -> 0
A48: Butter | B48: Pagett | C48: Ken | E48: =+Options!W48 -> 0 | G48: =SUM(D48:F48) -> 0 | I48: =+G48-H48 -> 0
A49: Quack | B49: Schoellman | C49: Walt | E49: =+Options!W49 -> 0 | G49: =SUM(D49:F49) -> 0 | I49: =+G49-H49 -> 0
A50: Honey | B50: Shields | C50: Jason | E50: =+Options!W50 -> 0 | G50: =SUM(D50:F50) -> 0 | I50: =+G50-H50 -> 0
A51: Gus | B51: Sokos | C51: Gus | E51: =+Options!W51 -> 0 | G51: =SUM(D51:F51) -> 0 | I51: =+G51-H51 -> 0
A52: Hood | B52: Sullivan | C52: Eric | E52: =+Options!W52 -> 0 | G52: =SUM(D52:F52) -> 0 | I52: =+G52-H52 -> 0
... A65: Gstan | B65: Young | C65: Mark | E65: =+Options!W65 -> 0 | G65: =SUM(D65:F65) -> 0 | I65: =+G65-H65 -> 0
D66: =SUM(D3:D65) -> 0 | E66: =SUM(E3:E65) -> 0 | G66: =SUM(G3:G65) -> 0 | H66: =SUM(H3:H65) -> 0 | I66: =SUM(I3:I65) -> 0
E67: =COUNTIF(E3:E66,"10") -> 0

Sheet Options
A1: Sponsor | B1: LastName | C1: FirstName | E1: Thursday | F1: Thursday | G1: =+F1 -> Thursday | H1: =+I1 -> Friday | I1: Friday | J1: =+I1 -> Friday | K1: =+L1 -> Saturday | L1: Saturday | M1: =+L1 -> Saturday | P1: Practice | T1: Whitey | U1: Monday | V1: Tuesday
E2: Team | F2: Skins | G2: Par 3 | H2: Team | I2: =+F2 -> Skins | J2: =+G2 -> Par 3 | K2: Team | L2: =+I2 -> Skins | M2: =+J2 -> Par 3 | N2: MELC | O2: Boland | P2: Round | Q2: Bro LD | R2: Bro LP | S2: 100 ft. | T2: PickEm | U2: Lodge | V2: Lodge | W2: Total
A3: Bro | B3: ='Mailing list'!B3 -> Alford | C3: ='Mailing list'!C3 -> Kyle | W3: =SUM(E3:V3) -> 0
A4: Sheik | B4: Bartlett | C4: Stacy | W4: =SUM(E4:V4) -> 0
A5: ='Mailing list'!A5 -> Dieterle | B5: ='Mailing list'!B5 -> Blankenburg | C5: ='Mailing list'!C5 -> Jeff | W5: =SUM(E5:V5) -> 0
A6: Slick/Gsta | B6: Bender | C6: Kyle | W6: =SUM(E6:V6) -> 0
A7: ='Mailing list'!A7 -> Patch | B7: ='Mailing list'!B7 -> Boland | C7: ='Mailing list'!C7 -> Pat | W7: =SUM(E7:V7) -> 0
A8: Gstan | B8: Brown | C8: Miles | W8: =SUM(E8:V8) -> 0
A9: Hood | B9: Buckey | C9: Dan | W9: =SUM(E9:V9) -> 0
A10: JT | B10: ='Mailing list'!B10 -> Carlstrom | C10: ='Mailing list'!C10 -> Brian | W10: =SUM(E10:V10) -> 0
A11: Gus | B11: Cobleigh | C11: Wayne | W11: =SUM(E11:V11) -> 0
A12: Whitey | B12: ='Mailing list'!B12 -> Combs | C12: ='Mailing list'!C12 -> Adam | W12: =SUM(E12:V12) -> 0
B13: ='Mailing list'!B13 -> Dosky | C13: ='Mailing list'!C13 -> Rick | W13: =SUM(E13:V13) -> 0
A14: ='Mailing list'!A14 -> Butter | B14: ='Mailing list'!B14 -> Flanagan | C14: ='Mailing list'!C14 -> Brian | W14: =SUM(E14:V14) -> 0
A15: ='Mailing list'!A15 -> Butter | B15: ='Mailing list'!B15 -> Flanagan | C15: Shane | W15: =SUM(E15:V15) -> 0
A16: ='Mailing list'!A16 -> Butter | B16: ='Mailing list'!B16 -> Garrett | C16: ='Mailing list'!C16 -> Greg | W16: =SUM(E16:V16) -> 0
A17: Spanky | B17: ='Mailing list'!B17 -> Green | C17: ='Mailing list'!C17 -> Ronell | W17: =SUM(E17:V17) -> 0
A18: Spanky | B18: ='Mailing list'!B18 -> Green | C18: ='Mailing list'!C18 -> Ronnie | W18: =SUM(E18:V18) -> 0
A19: Chef | B19: ='Mailing list'!B19 -> Greene | C19: ='Mailing list'!C19 -> Jon | W19: =SUM(E19:V19) -> 0
A20: Chef | B20: ='Mailing list'!B20 -> Granata | C20: ='Mailing list'!C20 -> Joe | W20: =SUM(E20:V20) -> 0
A21: Everybody | B21: Hagelberger | C21: Caleb | W21: =SUM(E21:V21) -> 0
A22: Caleb | B22: Hagelberger | C22: Matthew | W22: =SUM(E22:V22) -> 0
A23: Spanky | B23: Jackson | C23: Scott | W23: =SUM(E23:V23) -> 0
A24: ='Mailing list'!A24 -> Patch | B24: ='Mailing list'!B24 -> Kaniecki | C24: ='Mailing list'!C24 -> Brent | W24: =SUM(E24:V24) -> 0
A25: ='Mailing list'!A25 -> Gstan | B25: ='Mailing list'!B25 -> Kaniecki | C25: ='Mailing list'!C25 -> Eric | W25: =SUM(E25:V25) -> 0
A26: ='Mailing list'!A26 -> Gstan | B26: ='Mailing list'!B26 -> Kaniecki | C26: Jack | W26: =SUM(E26:V26) -> 0
A27: ='Mailing list'!A27 -> Gstan | B27: ='Mailing list'!B27 -> Kaniecki | C27: ='Mailing list'!C27 -> Mark | W27: =SUM(E27:V27) -> 0
A28: ='Mailing list'!A28 -> Gstan | B28: ='Mailing list'!B28 -> Kaniecki | C28: ='Mailing list'!C28 -> Stan | W28: =SUM(E28:V28) -> 0
A29: Monte | B29: ='Mailing list'!B29 -> Kassap | C29: ='Mailing list'!C29 -> Grant | W29: =SUM(E29:V29) -> 0
A30: Sheik | B30: Kellas | C30: Tom | W30: =SUM(E30:V30) -> 0
A31: Sensei | B31: Kelly | C31: Dan | W31: =SUM(E31:V31) -> 0
A32: Quack | B32: Kierner | C32: Rick | W32: =SUM(E32:V32) -> 0
A33: JT | B33: Langdon | C33: Matt | W33: =SUM(E33:V33) -> 0
A34: Butter | B34: ='Mailing list'!B34 -> Long | C34: ='Mailing list'!C34 -> Greg | W34: =SUM(E34:V34) -> 0
A35: ='Mailing list'!A35 -> Sheik | B35: ='Mailing list'!B35 -> Long | C35: ='Mailing list'!C35 -> Mike | W35: =SUM(E35:V35) -> 0
A36: Slick/Gsta | B36: ='Mailing list'!B36 -> Long | C36: Scott | W36: =SUM(E36:V36) -> 0
A37: ='Mailing list'!A37 -> Butter | B37: ='Mailing list'!B37 -> Lyme | C37: ='Mailing list'!C37 -> Brett | W37: =SUM(E37:V37) -> 0
A38: Butter | B38: ='Mailing list'!B38 -> Marshall | C38: ='Mailing list'!C38 -> Al | W38: =SUM(E38:V38) -> 0
A39: Patch | B39: ='Mailing list'!B39 -> McFarland | C39: ='Mailing list'!C39 -> Don | W39: =SUM(E39:V39) -> 0
A40: Butter | B40: ='Mailing list'!B40 -> Melick | C40: ='Mailing list'!C40 -> Eric | W40: =SUM(E40:V40) -> 0
A41: ='Mailing list'!#REF! -> #REF! | B41: ='Mailing list'!B41 -> Miller | C41: ='Mailing list'!C41 -> Christian | W41: =SUM(E41:V41) -> 0
A42: JT | B42: ='Mailing list'!B42 -> Montgomery | C42: Dan | W42: =SUM(E42:V42) -> 0
A43: JT | B43: ='Mailing list'!B43 -> Montgomery | C43: ='Mailing list'!C43 -> Mark | W43: =SUM(E43:V43) -> 0
A44: JT | B44: ='Mailing list'!B44 -> Moore | C44: ='Mailing list'!C44 -> Jeff | W44: =SUM(E44:V44) -> 0
A45: Bro | B45: ='Mailing list'!B45 -> Mullins | C45: ='Mailing list'!C45 -> Kevin | W45: =SUM(E45:V45) -> 0
A46: Bro | B46: ='Mailing list'!B46 -> Mullins | C46: Kurt | W46: =SUM(E46:V46) -> 0
A47: Brent | B47: ='Mailing list'!B47 -> Palazzolo | C47: ='Mailing list'!C47 -> Sal | W47: =SUM(E47:V47) -> 0
A48: Butter | B48: ='Mailing list'!B48 -> Pagett | C48: ='Mailing list'!C48 -> Ken | W48: =SUM(E48:V48) -> 0
A49: Gstan | B49: ='Mailing list'!B49 -> Schoellman | C49: ='Mailing list'!C49 -> Walt | W49: =SUM(E49:V49) -> 0
A50: Gstan | B50: Shields | C50: Jason | W50: =SUM(E50:V50) -> 0
A51: ='Mailing list'!A51 -> Gus | B51: ='Mailing list'!B51 -> Sokos | C51: ='Mailing list'!C51 -> Gus | W51: =SUM(E51:V51) -> 0
A52: Hood | B52: Sullivan | C52: Eric | W52: =SUM(E52:V52) -> 0
A53: Hood | B53: Sullivan | C53: Matthew | W53: =SUM(E53:V53) -> 0
A54: ='Mailing list'!A54 -> Gstan | B54: ='Mailing list'!B54 -> Syzmonski | C54: ='Mailing list'!C54 -> Bill | W54: =SUM(E54:V54) -> 0
A55: ='Mailing list'!A55 -> JT | B55: ='Mailing list'!B55 -> Thomas | C55: Colton | W55: =SUM(E55:V55) -> 0
A56: ='Mailing list'!A56 -> JT | B56: ='Mailing list'!B56 -> Thomas | C56: ='Mailing list'!C56 -> James | W56: =SUM(E56:V56) -> 0
A57: ='Mailing list'!A57 -> Quack | B57: Toth | C57: Michael | W57: =SUM(E57:V57) -> 0
A58: JT | B58: Washington | C58: Daron | W58: =SUM(E58:V58) -> 0
A59: ='Mailing list'!A59 -> Quack | B59: ='Mailing list'!B59 -> Watson | C59: ='Mailing list'!C59 -> Brian | W59: =SUM(E59:V59) -> 0
A60: ='Mailing list'!A60 -> Butter | B60: ='Mailing list'!B60 -> Watson | C60: ='Mailing list'!C60 -> Jason | W60: =SUM(E60:V60) -> 0
B61: ='Mailing list'!B61 -> White | C61: ='Mailing list'!C61 -> Aaron | W61: =SUM(E61:V61) -> 0
A62: Honey | B62: ='Mailing list'!B62 -> White | C62: Dave | W62: =SUM(E62:V62) -> 0
A63: Whitey | B63: ='Mailing list'!B63 -> White | C63: Don | W63: =SUM(E63:V63) -> 0
A64: Padre | B64: Yost | C64: Jeff | W64: =SUM(E64:V64) -> 0
A65: JT | B65: ='Mailing list'!B65 -> Young | C65: ='Mailing list'!C65 -> Mark | W65: =SUM(E65:V65) -> 0
B67: Entered | E67: =COUNTIF(E3:E66,"10") -> 0 | F67: =COUNTIF(F3:F65, "10") -> 0 | G67: =COUNTIF(G3:G65, "5") -> 0 | H67: =COUNTIF(H3:H65, "10") -> 0 | I67: =COUNTIF(I3:I65, "10") -> 0 | J67: =COUNTIF(J3:J65, "5") -> 0 | K67: =COUNTIF(K3:K65, "10") -> 0 | L67: =COUNTIF(L3:L65, "10") -> 0 | M67: =COUNTIF(M3:M65, "5") -> 0 | N67: =COUNTIF(N3:N65, "10") -> 0 | O67: =COUNTIF(O3:O65, "10") -> 0 | P67: =COUNTIF(P3:P65, "45") -> 0 | Q67: =COUNTIF(Q3:Q65, "15") -> 0 | R67: =COUNTIF(R3:R65, "15") -> 0 | S67: =COUNTIF(S3:S65, "5") -> 0 | T67: =COUNTIF(T3:T65, "10") -> 0 | U67: =COUNTIF(U3:U65, "65") -> 0 | V67: =COUNTIF(V3:V65, "80") -> 0 | W67: =SUM(W2:W66) -> 0 | Y67: =W67-P63*P67 -> 0
Z69: in hand
B70: Cash needed | C70: 100 | W70: =SUM(E70:V70) -> 0 | Y70: =W70*C70 -> 0 | Z70: 400 | AA70: =+Y70-Z70 -> -400 | AC70: =+AA70+AB70 -> -400
C71: 50 | W71: =SUM(E71:V71) -> 0 | Y71: =W71*C71 -> 0 | Z71: 100 | AA71: =+Y71-Z71 -> -100 | AC71: =+AA71+AB71 -> -100
C72: 20 | W72: =SUM(E72:V72) -> 0 | Y72: =W72*C72 -> 0 | Z72: 240 | AA72: =+Y72-Z72 -> -240 | AB72: 340 | AC72: =+AA72+AB72 -> 100
C73: 10 | W73: =SUM(E73:V73) -> 0 | Y73: =W73*C73 -> 0 | Z73: 120 | AA73: =+Y73-Z73 -> -120 | AC73: =+AA73+AB73 -> -120
C74: 5 | W74: =SUM(E74:V74) -> 0 | Y74: =W74*C74 -> 0 | AA74: =+Y74-Z74 -> 0 | AB74: 40 | AC74: =+AA74+AB74 -> 40
E76: =+E70*100+E71*50+E72*20+E73*10+E74*5 -> 0 | F76: =+F70*100+F71*50+F72*20+F73*10+F74*5 -> 0 | G76: =+G70*100+G71*50+G72*20+G73*10+G74*5 -> 0 | H76: =+H70*100+H71*50+H72*20+H73*10+H74*5 -> 0 | I76: =+I70*100+I71*50+I72*20+I73*10+I74*5 -> 0 | J76: =+J70*100+J71*50+J72*20+J73*10+J74*5 -> 0 | K76: =+K70*100+K71*50+K72*20+K73*10+K74*5 -> 0 | L76: =+L70*100+L71*50+L72*20+L73*10+L74*5 -> 0 | ... O76: =+O70*100+O71*50+O72*20+O73*10+O74*5 -> 0 | Q76: =+Q70*100+Q71*50+Q72*20+Q73*10+Q74*5 -> 0 | R76: =+R70*100+R71*50+R72*20+R73*10+R74*5 -> 0 | S76: =+S70*100+S71*50+S72*20+S73*10+S74*5 -> 0 | T76: =+T70*100+T71*50+T72*20+T73*10+T74*5 -> 0 | U76: =+U70*100+U71*50+U72*20+U73*10+U74*5 -> 0 | V76: =+V70*100+V71*50+V72*20+V73*10+V74*5 -> 0 | W76: =+W70*100+W71*50+W72*20+W73*10+W74*5 -> 0 | Y76: =SUM(Y70:Y75) -> 0 | Z76: =SUM(Z70:Z74) -> 860 | AA76: =SUM(AA70:AA74) -> -860 | AC76: =SUM(AC70:AC74) -> -480
Y77: 380 | AA77: =+Y77-Z77 -> 380
E78: =+E67*10-E76 -> 0 | F78: =+F67*10-F76 -> 0 | G78: =+G67*5-G76 -> 0 | H78: =+H67*10-H76 -> 0 | I78: =+I67*10-I76 -> 0 | J78: =+J67*5-J76 -> 0 | K78: =+K67*10-K76 -> 0 | L78: =+L67*10-L76 -> 0 | M78: =+M67*5-M76 -> 0 | N78: =+N67*10-N76 -> 0 | O78: =+O67*10-O76 -> 0 | Q78: =SUM(Q3:Q65)-Q76 -> 0 | R78: =SUM(R3:R65)-R76 -> 0 | S78: =+S67*5-S76 -> 0 | T78: =+T67*10-T76 -> 0 | Y78: =+Y76+Y77 -> 380 | Z78: =+Z76+Z77 -> 860 | AA78: =+AA76+AA77 -> -480 | AC78: =+AC76+AC77 -> -480
Q80: 115 | R80: 185
Q81: 120 | R81: 200
Q82: 120 | R82: 190

Sheet venmo

Sheet GFFL
C6: High points
C7: Week 1 | D7: Week 2 | E7: Week 3 | F7: Week 4 | G7: Week 5 | H7: Week 6 | I7: Week 7 | J7: Week 8 | K7: Week 9 | L7: Week 10 | M7: Week 11 | N7: Week 12 | O7: Week 13 | P7: Week 14 | Q7: Total Weeks | R7: Playoffs | S7: Total
A8: BoMan | Q8: =SUM(C8:P8) -> 0 | R8: 300 | S8: =Q8+R8 -> 300
A9: JT | G9: 30 | Q9: =SUM(C9:P9) -> 30 | S9: =Q9+R9 -> 30
A10: Killer | I10: 30 | L10: 30 | P10: 30 | Q10: =SUM(C10:P10) -> 90 | R10: 50 | S10: =Q10+R10 -> 140 | W10: 1st | X10: 300
A11: Whitey | M11: 30 | Q11: =SUM(C11:P11) -> 30 | S11: =Q11+R11 -> 30 | W11: 2nd | X11: 150
A12: Randy | E12: 30 | Q12: =SUM(C12:P12) -> 30 | S12: =Q12+R12 -> 30 | W12: 3rd | X12: 100
A13: KGB | Q13: =SUM(C13:P13) -> 0 | S13: =Q13+R13 -> 0 | W13: 4th | X13: 50
A14: Spanky | C14: 30 | Q14: =SUM(C14:P14) -> 30 | S14: =Q14+R14 -> 30
A15: Kid | K15: 30 | O15: 30 | Q15: =SUM(C15:P15) -> 60 | R15: 150 | S15: =Q15+R15 -> 210
A16: Spyder | Q16: =SUM(C16:P16) -> 0 | S16: =Q16+R16 -> 0
A17: Sheik | Q17: =SUM(C17:P17) -> 0 | S17: =Q17+R17 -> 0
A18: Real Stan | D18: 30 | H18: 30 | N18: 30 | Q18: =SUM(C18:P18) -> 90 | R18: 100 | S18: =Q18+R18 -> 190
A19: Chef | F19: 30 | J19: 30 | Q19: =SUM(C19:P19) -> 60 | S19: =Q19+R19 -> 60
S21: =SUM(S8:S20) -> 1020
A22: Weekly payouts | D22: 30
AD39: =+AD37-373 -> -373

Sheet moonshine
B4: Jars | C4: Lids | D4: Tax | E4: Tip | F4: Total
A5: BoMan | B5: 23 | C5: =6*T25 -> 0 | D5: =(B5+C5)*0.07 -> 1.61 | F5: =SUM(B5:E5) -> 24.61
A6: Butter | B6: 23 | C6: =6*T26 -> 0 | D6: =(B6+C6)*0.07 -> 1.61 | F6: =SUM(B6:E6) -> 24.61
A7: Chef | B7: =23*6+1 -> 139 | C7: =6*T28 -> 0 | D7: =(B7+C7)*0.07 -> 9.73 | F7: =SUM(B7:E7) -> 148.73
A8: Spanky | B8: =23+17 -> 40 | C8: =6*T29 -> 0 | D8: =(B8+C8)*0.07 -> 2.8 | F8: =SUM(B8:E8) -> 42.8
A9: Fun Dan | B9: 17 | C9: =6*T30 -> 0 | D9: =(B9+C9)*0.07 -> 1.19 | F9: =SUM(B9:E9) -> 18.19
A10: Minardi | B10: 17 | C10: =6*T31 -> 0 | D10: =(B10+C10)*0.07 -> 1.19 | F10: =SUM(B10:E10) -> 18.19
A11: Killer | B11: =23+23 -> 46 | C11: =6*T32 -> 0 | D11: =(B11+C11)*0.07 -> 3.22 | F11: =SUM(B11:E11) -> 49.22
A12: BDubs | B12: 34 | C12: =6*T32 -> 0 | D12: =(B12+C12)*0.07 -> 2.38 | F12: =SUM(B12:E12) -> 36.38
A13: Bro | B13: 69 | D13: =(B13+C13)*0.07 -> 4.83 | F13: =SUM(B13:E13) -> 73.83
A14: Spyder | B14: 23 | C14: =6*T36 -> 0 | D14: =(B14+C14)*0.07 -> 1.61 | F14: =SUM(B14:E14) -> 24.61
B15: =SUM(B5:B14) -> 431 | C15: =SUM(C5:C14) -> 0 | D15: =SUM(D5:D14) -> 30.17 | E15: =SUM(E5:E14) -> 0 | F15: =SUM(F5:F14) -> 461.17
H17: pd
F19: =F17+F15 -> 461.17
A23: Choc Milk | B23: 3
A24: Choc PB | B24: 2
A25: Lucky | B25: 7 | H25: BoMan
A26: Monkey | B26: 2 | H26: Butter
A27: Debby | B27: 1 | H27: Cdubs
H28: Chef
H29: Gstan
H30: Honey
H31: JT
H32: KGB
H33: Killer
H34: Sheiker
H35: Sizeten
H36: Spyder
H37: Total
H40: Fun Dan | I40: Mini Orange Push-Up
H41: Fun Dan | I41: Root beer float

Sheet balances
D1: BDubs | E1: Super Bowl | F1: Super Bowl | G1: Super Bowl | H1: Super Bowl | I1: Spanky | J1: Spanky | K1: NCAA | M1: BDubs NCAA | N1: BDubs | O1: BoMan | P1: Misc To/From | S1: GXXV | AC1: Super Bowl | AD1: Super Bowl | AE1: Super Bowl | AF1: BDubs
B2: GXXX | C2: GFFL | D2: NFL Weekly | E2: Knockout 1 | F2: Knockout 2 | G2: Knockout 3 | H2: Block Pool | I2: G SB Pool | J2: Bro SB Pool | K2: Knockout | L2: BroMadness | M2: Knockout | N2: Squares | O2: Bracket | P2: Sheiker | Q2: Other | R2: Total | S2: Payments | T2: Carryover | AC2: Knockout 1 | AD2: Knockout 2 | AE2: Knockout 3 | AF2: NFL Weekly
A3: BDubs | B3: =10-30-20 -> -40 | D3: 10 | F3: 50 | O3: 20 | R3: =SUM(B3:Q3) -> 40 | AC3: 50 | AD3: 50 | AF3: 90
A4: Alf | B4: -20 | E4: 400 | O4: 20 | R4: =SUM(B4:Q4) -> 400 | AD4: 50 | AF4: 20
A5: Black Doug | R5: =SUM(B5:Q5) -> 0
A6: BoMan | B6: =20+200-100-30-20-20-20+300-85-60+300 -> 485 | C6: =300-300+85 -> 85 | D6: 60 | K6: 20 | O6: 60 | R6: =SUM(B6:Q6) -> 710 | T6: =+R6+S6 -> 710 | AD6: 50 | AE6: 50 | AF6: 170
A7: Bro | B7: =5+10-65-15-30-20-40-20-20 -> -195 | D7: =20-20 -> 0 | F7: 50 | K7: 20 | O7: 20 | P7: =65+40+385-74 -> 416 | Q7: 490 | R7: =SUM(B7:Q7) -> 801 | T7: =+R7+S7 -> 801 | AC7: 50 | AD7: 50 | AF7: 90
A8: Bubba | B8: 10 | R8: =SUM(B8:Q8) -> 10 | AF8: 20
A9: Butter | B9: =45+10-30-20 -> 5 | K9: 20 | R9: =SUM(B9:Q9) -> 25 | T9: =+R9+S9 -> 25 | AF9: 10
A10: Caleb | R10: =SUM(B10:Q10) -> 0 | T10: =+R10+S10 -> 0 | AC10: 50 | AE10: 50 | AF10: 100
A11: CDubs | B11: =40-40 -> 0 | D11: =30-30 -> 0 | H11: 250 | R11: =SUM(B11:Q11) -> 250 | AD11: 50 | AE11: 50 | AF11: 20
A12: Cerrano | B12: 20 | R12: =SUM(B12:Q12) -> 20
A13: Chef | B13: =10-10-30-20-20-85 -> -155 | C13: =60-60+85 -> 85 | G13: 50 | H13: 125 | K13: 20 | O13: 20 | P13: -5 | R13: =SUM(B13:Q13) -> 140 | T13: =+R13+S13 -> 140 | AE13: 50 | AF13: 50
A14: Colt 45 | B14: =10-10-50-30-20 -> -100 | D14: =40-40 -> 0 | Q14: =50+30+20 -> 100 | R14: =SUM(B14:Q14) -> 0 | T14: =+R14+S14 -> 0
A15: Daniel-san | B15: 10 | R15: =SUM(B15:Q15) -> 10
A16: Dosky | R16: =SUM(B16:Q16) -> 0 | AC16: 50 | AF16: 30
A17: Double G | B17: =10-10 -> 0 | D17: =70-50-20 -> 0 | R17: =SUM(B17:Q17) -> 0 | T17: =+R17+S17 -> 0 | AF17: 20
A18: Fun Dan | B18: =5+10 -> 15 | D18: 40 | O18: 20 | R18: =SUM(B18:Q18) -> 75
A19: Grandpa Al | R19: =SUM(B19:Q19) -> 0 | AE19: 50 | AF19: 10
A20: GStan | B20: =10-10-30-20-20 -> -70 | F20: 200 | G20: 400 | I20: 750 | Q20: -490 | R20: =SUM(B20:Q20) -> 790 | T20: =+R20+S20 -> 790 | AC20: 50 | AF20: 80
A21: Gus | B21: -20 | D21: =150-100-40 -> 10 | G21: 50 | K21: 20 | P21: =47+10 -> 57 | Q21: -97 | R21: =SUM(B21:Q21) -> 20 | T21: =+R21+S21 -> 20
A22: Hammer | R22: =SUM(B22:Q22) -> 0 | AC22: 50 | AD22: 50 | AF22: 140
A23: Honey | B23: =600+20-30-40 -> 550 | D23: 60 | H23: 250 | R23: =SUM(B23:Q23) -> 860 | T23: =+R23+S23 -> 860 | AC23: 50 | AE23: 50 | AF23: 70
A24: JT | B24: =120-100+300-30-20-40-20+30-85-20 -> 135 | C24: =30-30+85 -> 85 | D24: 90 | K24: 20 | O24: 20 | Q24: =-50-30-20 -> -100 | R24: =SUM(B24:Q24) -> 250 | T24: =+R24+S24 -> 250
A25: J Mo | R25: =SUM(B25:Q25) -> 0 | AD25: 50 | AE25: 50 | AF25: 40
A26: KGB | B26: =10-10-30 -> -30 | D26: =20-20 -> 0 | E26: 50 | K26: 20 | R26: =SUM(B26:Q26) -> 40 | T26: =+R26+S26 -> 40
A27: Kid Rock | B27: 105 | C27: =105-105 -> 0 | K27: 20 | P27: -105 | R27: =SUM(B27:Q27) -> 20 | T27: =+R27+S27 -> 20
A28: Kierner | R28: =SUM(B28:Q28) -> 0 | AD28: 50 | AE28: 50 | AF28: 70
A29: Killer | B29: =15+5+20-30-20-40-20+40+300 -> 270 | C29: =140-100-40 -> 0 | D29: 40 | K29: 20 | O29: 40 | R29: =SUM(B29:Q29) -> 370 | T29: =+R29+S29 -> 370 | AD29: 50 | AE29: 50 | AF29: 90
A30: Long-O | B30: 10 | R30: =SUM(B30:Q30) -> 10 | AD30: 50
A31: LT | B31: =10-10 -> 0 | D31: =20-20 -> 0 | R31: =SUM(B31:Q31) -> 0 | AC31: 50 | AD31: 50
A32: Meat / Beef | B32: =10-10-30-40 -> -70 | D32: =20-20 -> 0 | E32: 200 | G32: 200 | R32: =SUM(B32:Q32) -> 330 | AC32: 50 | AD32: 50
A33: Minardi | O33: 20 | R33: =SUM(B33:Q33) -> 20 | T33: =+R33+S33 -> 20
A34: Monte | B34: =500-100+100-30-40 -> 430 | D34: 20 | F34: 400 | R34: =SUM(B34:Q34) -> 850 | T34: =+R34+S34 -> 850
A35: Monte Jr | B35: 150 | R35: =SUM(B35:Q35) -> 150 | T35: =+R35+S35 -> 150 | AF35: 40
A36: Padre | B36: =5+10 -> 15 | R36: =SUM(B36:Q36) -> 15 | AD36: 50 | AE36: 50 | AF36: 70
A37: Quack | B37: 500 | K37: 20 | R37: =SUM(B37:Q37) -> 520 | T37: =+R37+S37 -> 520 | AC37: 50 | AE37: 50
A38: Randy | B38: =10-10-20-85-20 -> -125 | C38: =30-30+85 -> 85 | D38: =40-40 -> 0 | H38: 125 | J38: 500 | K38: 20 | O38: 20 | P38: -500 | R38: =SUM(B38:Q38) -> 125 | T38: =+R38+S38 -> 125
A39: Real Stan | B39: 140 | C39: =190-50-140 -> 0 | K39: 20 | P39: -140 | R39: =SUM(B39:Q39) -> 20 | T39: =+R39+S39 -> 20
A40: Dr. Sal | R40: =SUM(B40:Q40) -> 0 | T40: =+R40+S40 -> 0 | AC40: 50 | AD40: 50 | AF40: 50
A41: Scoots | B41: =210+20-20-20 -> 190 | O41: =20+20 -> 40 | R41: =SUM(B41:Q41) -> 230
A42: Sensei | B42: =10-10 -> 0 | M42: 20 | N42: 60 | O42: 40 | R42: =SUM(B42:Q42) -> 120 | T42: =+R42+S42 -> 120 | AC42: 50 | AD42: 50 | AF42: 10
A43: Shane | R43: =SUM(B43:Q43) -> 0
A44: Sheiker | B44: =20+300-100-30-40-40-20-30-85-20+250 -> 205 | C44: 85 | D44: 10 | E44: 50 | K44: 20 | O44: 20 | P44: =-65+140-47-40+5+500-385+105-10+74 -> 277 | R44: =SUM(B44:Q44) -> 667 | T44: =+R44+S44 -> 667 | AC44: 50 | AE44: 50 | AF44: 100
A45: Sizeten | B45: 20 | R45: =SUM(B45:Q45) -> 20 | T45: =+R45+S45 -> 20 | AC45: 50 | AE45: 50 | AF45: 10
A46: Sleepy | R46: =SUM(B46:Q46) -> 0 | T46: =+R46+S46 -> 0
A47: Spnaky | B47: =20-20 -> 0 | C47: =30-30 -> 0 | D47: =20-20 -> 0 | K47: 20 | O47: 20 | R47: =SUM(B47:Q47) -> 40 | T47: =+R47+S47 -> 40
A48: Spyder | B48: =10-10 -> 0 | D48: =80-50-30 -> 0 | R48: =SUM(B48:Q48) -> 0 | T48: =+R48+S48 -> 0
A49: Sully | R49: =SUM(B49:Q49) -> 0
A50: Uncle Mark | R50: =SUM(B50:Q50) -> 0 | AE50: 50 | AF50: 10
A51: VJ | R51: =SUM(B51:Q51) -> 0 | T51: =+R51+S51 -> 0
A52: Walt | R52: =SUM(B52:Q52) -> 0 | AC52: 50
A53: Whitey | B53: =5+500-85+10-30-40-20+30-85-60 -> 225 | C53: =30-30+85 -> 85 | D53: 70 | H53: 250 | K53: 20 | N53: 60 | R53: =SUM(B53:Q53) -> 710 | T53: =+R53+S53 -> 710 | AC53: =SUM(AC3:AC52) -> 750 | AD53: =SUM(AD3:AD52) -> 750 | AE53: =SUM(AE3:AE52) -> 700 | AF53: =SUM(AF3:AF52) -> 1410
A54: Whitey Jr | R54: =SUM(B54:Q54) -> 0 | T54: =+R54+S54 -> 0
A55: Winthorp | B55: =125+20-100-40 -> 5 | D55: 10 | K55: 20 | R55: =SUM(B55:Q55) -> 35 | T55: =+R55+S55 -> 35
B56: =SUM(B3:B55) -> 2670 | C56: =SUM(C3:C55) -> 510 | D56: =SUM(D3:D55) -> 420 | E56: =SUM(E3:E55) -> 700 | F56: =SUM(F3:F55) -> 700 | G56: =SUM(G3:G55) -> 700 | H56: =SUM(H3:H55) -> 1000 | I56: =SUM(I3:I55) -> 750 | ... T56: =SUM(T3:T55) -> 7303
A58: GXXX trip fund | B58: =-505+50+50 -> -405 | R58: =SUM(B58:Q58) -> -405
A62: Kid Rock
A63: 1366 Weybridge Rd
A64: Columbus OH 43220 | S64: Wilson
S65: server
R66: =SUM(R56:R65) -> 8288 | AC66: =700-AC64-AC65-AC67-AC68 -> 700 | AD66: =700-AD64-AD65-AD67-AD68 -> 700 | AE66: =700-AE64-AE65-AE67-AE68 -> 700
AC67: 0 | AD67: 0 | AE67: 0
R68: =860+1350+120+40 -> 2370 | U68: cash
R70: =+R66-R68 -> 5918 | U70: 46104
